setup.cfg
setup.py
tlpconfig
./README.md
./VERSION
./__init__.py
./requirements.txt
./tlpconfig
./data/categories.json
./data/help
./data/ui/about.ui
./data/ui/application.css
./data/ui/header.ui
./data/ui/shell.ui
./data/ui/status.ui
./data/ui/window.ui
./data/ui/categories/audio.ui
./data/ui/categories/battery_charge_thresholds.ui
./data/ui/categories/disks_and_controllers.ui
./data/ui/categories/drive_slot_ultrabay.ui
./data/ui/categories/file_system.ui
./data/ui/categories/graphics_cards.ui
./data/ui/categories/kernel.ui
./data/ui/categories/networking.ui
./data/ui/categories/pci_express_bus.ui
./data/ui/categories/processor_and_frequence_scaling.ui
./data/ui/categories/runtime_power_management.ui
./data/ui/categories/system_start_and_shutdown.ui
./data/ui/categories/undervolting.ui
./data/ui/categories/usb.ui
./data/ui/categories/wireless_radio_switch.ui
./tlp/__init__.py
./tlp/application.py
./tlp/resources.py
./tlp/models/__init__.py
./tlp/models/configuration.py
./tlp/models/group.py
./tlp/models/parameter.py
./tlp/models/parameter_loader.py
./tlp/models/status.py
./tlp/views/__init__.py
./tlp/views/categories_group.py
./tlp/views/shell.py
./tlp/views/status.py
./tlp/views/view_loader.py
./tlp/views/window.py
./tlp/views/binders/__init__.py
./tlp/views/binders/default_binders.py
./tlp/views/binders/free_text.py
./tlp/views/binders/selector.py
./tlp/views/categories/__init__.py
./tlp/views/categories/audio.py
./tlp/views/categories/battery_charge_thresholds.py
./tlp/views/categories/category.py
./tlp/views/categories/disks_and_controllers.py
./tlp/views/categories/drive_slot_ultrabay.py
./tlp/views/categories/file_system.py
./tlp/views/categories/graphics_cards.py
./tlp/views/categories/kernel.py
./tlp/views/categories/networking.py
./tlp/views/categories/pci_express_bus.py
./tlp/views/categories/processor_and_frequence_scaling.py
./tlp/views/categories/runtime_power_management.py
./tlp/views/categories/system_start_and_shutdown.py
tlpconfig.egg-info/PKG-INFO
tlpconfig.egg-info/SOURCES.txt
tlpconfig.egg-info/dependency_links.txt
tlpconfig.egg-info/requires.txt
tlpconfig.egg-info/top_level.txt