Metadata-Version: 1.1
Name: tlpconfig
Version: 0.2-
Summary: A GTK+ 3.10 app to configure TLP.
Home-page: https://github.com/fholiveira/tlpconfig
Author: Fernando Oliveira
Author-email: fernando@fholiveira.com
License: BSD
Download-URL: https://github.com/fholiveira/tlpconfig/tarball/0.2
